llama_index/multi_modal_llms/bedrock/__init__.py
llama_index/multi_modal_llms/bedrock/base.py
llama_index/multi_modal_llms/bedrock/utils.py
llama_index_multi_modal_llms_bedrock-0.2.1.dist-info/METADATA
llama_index_multi_modal_llms_bedrock-0.2.1.dist-info/WHEEL
llama_index_multi_modal_llms_bedrock-0.2.1.dist-info/licenses/LICENSE
llama_index_multi_modal_llms_bedrock-0.2.1.dist-info/RECORD
