Metadata-Version: 2.4
Name: llama-index-multi-modal-llms-bedrock
Version: 0.2.1
Summary: llama-index multi-modal llms bedrock integration
Author: LlamaIndex
License-Expression: MIT
License-File: LICENSE
Requires-Python: <4.0,>=3.9
Requires-Dist: aioboto3>=12.3.0
Requires-Dist: boto3>=1.34.0
Requires-Dist: llama-index-core<0.15,>=0.13.0
Requires-Dist: llama-index-llms-bedrock-converse<0.9,>=0.8.0
